Metadata-Version: 1.0
Name: kindlelamp
Version: 1.0
Summary: Kindleの蔵書一覧を取得します
Home-page: https://github.com/koboriakira/kindlelamp
Author: Kobori Akira
Author-email: private.beats@gmail.com
License: UNKNOWN
Platform: UNKNOWN
